torchft-0.1.1.dist-info/METADATA
torchft-0.1.1.dist-info/WHEEL
torchft-0.1.1.dist-info/entry_points.txt
torchft-0.1.1.dist-info/licenses/LICENSE
torchft/__init__.py
torchft/checkpointing.py
torchft/checkpointing_test.py
torchft/data.py
torchft/data_test.py
torchft/ddp.py
torchft/ddp_test.py
torchft/futures.py
torchft/futures_test.py
torchft/http.py
torchft/local_sgd.py
torchft/local_sgd_test.py
torchft/manager.py
torchft/manager_integ_test.py
torchft/manager_test.py
torchft/optim.py
torchft/optim_test.py
torchft/parameter_server.py
torchft/parameter_server_test.py
torchft/process_group.py
torchft/process_group_test.py
torchft/torchft.pyi
torchft/torchft.cpython-311-x86_64-linux-gnu.so
torchft-0.1.1.dist-info/RECORD
