Metadata-Version: 2.4
Name: torchft
Version: 0.1.1
Classifier: Programming Language :: Rust
Classifier: Programming Language :: Python :: Implementation :: CPython
Classifier: Programming Language :: Python :: Implementation :: PyPy
Requires-Dist: torch
Requires-Dist: pytest ; extra == 'dev'
Requires-Dist: black ; extra == 'dev'
Requires-Dist: pyre-check ; extra == 'dev'
Requires-Dist: parameterized ; extra == 'dev'
Provides-Extra: dev
License-File: LICENSE
Requires-Python: >=3.8
Project-URL: Documentation, https://pytorch-labs.github.io/torchft
Project-URL: Repository, https://github.com/pytorch-labs/torchft
Project-URL: Issues, https://github.com/pytorch-labs/torchft/issues
